<annotation>
	<folder>無齒</folder>
	<filename>377-20.jpg</filename>
	<path>D:\阿杰\無齒\377-20.jpg</path>
	<source>
		<database>Unknown</database>
	</source>
	<size>
		<width>1920</width>
		<height>1080</height>
		<depth>3</depth>
	</size>
	<segmented>0</segmented>
	<object>
		<name>Gnathanodon speciosus</name>
		<pose>Unspecified</pose>
		<truncated>0</truncated>
		<difficult>0</difficult>
		<bndbox>
			<xmin>849</xmin>
			<ymin>59</ymin>
			<xmax>1267</xmax>
			<ymax>406</ymax>
		</bndbox>
	</object>
	<object>
		<name>Gnathanodon speciosus</name>
		<pose>Unspecified</pose>
		<truncated>0</truncated>
		<difficult>0</difficult>
		<bndbox>
			<xmin>413</xmin>
			<ymin>299</ymin>
			<xmax>783</xmax>
			<ymax>582</ymax>
		</bndbox>
	</object>
	<object>
		<name>Gnathanodon speciosus</name>
		<pose>Unspecified</pose>
		<truncated>0</truncated>
		<difficult>0</difficult>
		<bndbox>
			<xmin>939</xmin>
			<ymin>343</ymin>
			<xmax>1354</xmax>
			<ymax>658</ymax>
		</bndbox>
	</object>
	<object>
		<name>Gnathanodon speciosus</name>
		<pose>Unspecified</pose>
		<truncated>0</truncated>
		<difficult>0</difficult>
		<bndbox>
			<xmin>1202</xmin>
			<ymin>472</ymin>
			<xmax>1427</xmax>
			<ymax>694</ymax>
		</bndbox>
	</object>
	<object>
		<name>Gnathanodon speciosus</name>
		<pose>Unspecified</pose>
		<truncated>0</truncated>
		<difficult>0</difficult>
		<bndbox>
			<xmin>1384</xmin>
			<ymin>359</ymin>
			<xmax>1849</xmax>
			<ymax>593</ymax>
		</bndbox>
	</object>
	<object>
		<name>Gnathanodon speciosus</name>
		<pose>Unspecified</pose>
		<truncated>0</truncated>
		<difficult>0</difficult>
		<bndbox>
			<xmin>1050</xmin>
			<ymin>702</ymin>
			<xmax>1603</xmax>
			<ymax>930</ymax>
		</bndbox>
	</object>
	<object>
		<name>Gnathanodon speciosus</name>
		<pose>Unspecified</pose>
		<truncated>0</truncated>
		<difficult>0</difficult>
		<bndbox>
			<xmin>775</xmin>
			<ymin>621</ymin>
			<xmax>1002</xmax>
			<ymax>885</ymax>
		</bndbox>
	</object>
	<object>
		<name>Gnathanodon speciosus</name>
		<pose>Unspecified</pose>
		<truncated>0</truncated>
		<difficult>0</difficult>
		<bndbox>
			<xmin>396</xmin>
			<ymin>568</ymin>
			<xmax>822</xmax>
			<ymax>881</ymax>
		</bndbox>
	</object>
</annotation>
